clustering/__init__.py
clustering/cluster.py
clustering/helper.py
coar-0.1.dist-info/LICENSE
coar-0.1.dist-info/METADATA
coar-0.1.dist-info/WHEEL
coar-0.1.dist-info/top_level.txt
coar-0.1.dist-info/RECORD
